flaskoidc/__init__.py
flaskoidc/config.py
flaskoidc/models.py
adsk_flaskoidc-1.0.4.dist-info/LICENSE
adsk_flaskoidc-1.0.4.dist-info/METADATA
adsk_flaskoidc-1.0.4.dist-info/WHEEL
adsk_flaskoidc-1.0.4.dist-info/top_level.txt
adsk_flaskoidc-1.0.4.dist-info/RECORD
