Metadata-Version: 2.1
Name: adsk-flaskoidc
Version: 1.0.4
Summary: Flask wrapper with pre-configured OAuth2 and OIDC support
Home-page: https://github.com/mcohen01/flaskoidc.git
Author: Michael Cohen
Author-email: mcohen01@gmail.com
License: UNKNOWN
Platform: UNKNOWN
Requires-Python: >=3.6
Requires-Dist: Flask (>=1.0.2)
Requires-Dist: Authlib (==0.15.4)
Requires-Dist: requests (==2.25.1)
Requires-Dist: Flask-SQLAlchemy (==2.5.1)
